docker_checks/__init__.py
docker_checks/check_add.py
docker_checks/check_arg_env.py
docker_checks/check_from.py
docker_checks/check_healthcheck.py
docker_checks/check_port.py
docker_checks/check_root.py
docker_checks/check_upgrade.py
docker_checks-0.0.23.dist-info/METADATA
docker_checks-0.0.23.dist-info/WHEEL
docker_checks-0.0.23.dist-info/top_level.txt
docker_checks-0.0.23.dist-info/RECORD
